{
  "title": "Dipali & Neil.",
  "images": [
    {
      "id": 1,
      "src": "/couples/dipali_neil/A7401891-Edit-min.webp",
      "alt": "Photo 1",
      "height": 785
    },
    {
      "id": 2,
      "src": "/couples/dipali_neil/A7401920-Edit-min.webp",
      "alt": "Photo 2",
      "height": 799
    },
    {
      "id": 3,
      "src": "/couples/dipali_neil/A7401942-min.webp",
      "alt": "Photo 3",
      "height": 589
    },
    {
      "id": 4,
      "src": "/couples/dipali_neil/A7401962-min.webp",
      "alt": "Photo 4",
      "height": 556
    },
    {
      "id": 5,
      "src": "/couples/dipali_neil/A7402073-Edit-min.webp",
      "alt": "Photo 5",
      "height": 580
    },
    {
      "id": 6,
      "src": "/couples/dipali_neil/A7402124-min.webp",
      "alt": "Photo 6",
      "height": 702
    },
    {
      "id": 7,
      "src": "/couples/dipali_neil/A7402130-Edit-min.webp",
      "alt": "Photo 7",
      "height": 688
    },
    {
      "id": 8,
      "src": "/couples/dipali_neil/A7402161-Edit-min.webp",
      "alt": "Photo 8",
      "height": 689
    },
    {
      "id": 9,
      "src": "/couples/dipali_neil/A7402621-Edit-min.webp",
      "alt": "Photo 9",
      "height": 654
    },
    {
      "id": 10,
      "src": "/couples/dipali_neil/Front image for banner.webp",
      "alt": "Photo 10",
      "height": 766
    }
  ]
}